<?xml version="1.0" encoding="UTF-8"?><record_update>
    <sys_ui_related action="DELETE" sys_domain="global" table="x_g_sonc_ns_pro_port_connection" version="2" view="nspro">
        <sys_ui_related_list_entry action="INSERT_OR_UPDATE">
            <filter/>
            <list_id display_value="Port Connection - NSPro" name="x_g_sonc_ns_pro_port_connection" related_list="NULL" sys_domain="global" view="7d269f741be1fd10824752c1604bcb31">a35d2ae41b07b150824752c1604bcbdf</list_id>
            <order_by/>
            <position>0</position>
            <related_list/>
            <sys_class_name>sys_ui_related_list_entry</sys_class_name>
            <sys_created_by>wbbusby</sys_created_by>
            <sys_created_on>2023-12-08 13:19:19</sys_created_on>
            <sys_id>635d2ae41b07b150824752c1604bcbe0</sys_id>
            <sys_mod_count>0</sys_mod_count>
            <sys_updated_by>wbbusby</sys_updated_by>
            <sys_updated_on>2023-12-08 13:19:19</sys_updated_on>
        </sys_ui_related_list_entry>
        <sys_ui_related_list action="INSERT_OR_UPDATE">
            <calculated_name>Port Connection - NSPro</calculated_name>
            <filter/>
            <name>x_g_sonc_ns_pro_port_connection</name>
            <order_by/>
            <position/>
            <related_list/>
            <sys_class_name>sys_ui_related_list</sys_class_name>
            <sys_created_by>wbbusby</sys_created_by>
            <sys_created_on>2023-12-08 13:19:19</sys_created_on>
            <sys_domain>global</sys_domain>
            <sys_domain_path>/</sys_domain_path>
            <sys_id>a35d2ae41b07b150824752c1604bcbdf</sys_id>
            <sys_mod_count>0</sys_mod_count>
            <sys_name>Port Connection - NSPro</sys_name>
            <sys_package display_value="NS Pro" source="x_g_sonc_ns_pro">b5683ae81b157110824752c1604bcbc0</sys_package>
            <sys_policy/>
            <sys_scope display_value="NS Pro">b5683ae81b157110824752c1604bcbc0</sys_scope>
            <sys_update_name>sys_ui_related_x_g_sonc_ns_pro_port_connection_nspro</sys_update_name>
            <sys_updated_by>wbbusby</sys_updated_by>
            <sys_updated_on>2023-12-08 13:19:19</sys_updated_on>
            <sys_user/>
            <view display_value="NSPro" name="nspro">7d269f741be1fd10824752c1604bcb31</view>
            <view_name/>
        </sys_ui_related_list>
    </sys_ui_related>
    <sys_update_version action="INSERT_OR_UPDATE">
        <action>DELETE</action>
        <application display_value="NS Pro">b5683ae81b157110824752c1604bcbc0</application>
        <file_path/>
        <instance_id>efe2cdc7db351c10bc8b7f693296192d</instance_id>
        <instance_name>ncgovappdev</instance_name>
        <name>sys_ui_related_x_g_sonc_ns_pro_port_connection_nspro</name>
        <payload><![CDATA[<?xml version="1.0" encoding="UTF-8"?><record_update><sys_ui_related sys_domain="global" table="x_g_sonc_ns_pro_port_connection" version="2" view="nspro"><sys_ui_related_list_entry action="INSERT_OR_UPDATE"><filter/><list_id display_value="Port Connection - NSPro" name="x_g_sonc_ns_pro_port_connection" related_list="NULL" sys_domain="global" view="7d269f741be1fd10824752c1604bcb31">a35d2ae41b07b150824752c1604bcbdf</list_id><order_by/><position>0</position><related_list/><sys_class_name>sys_ui_related_list_entry</sys_class_name><sys_created_by>wbbusby</sys_created_by><sys_created_on>2023-12-08 13:19:19</sys_created_on><sys_id>635d2ae41b07b150824752c1604bcbe0</sys_id><sys_mod_count>0</sys_mod_count><sys_updated_by>wbbusby</sys_updated_by><sys_updated_on>2023-12-08 13:19:19</sys_updated_on></sys_ui_related_list_entry><sys_ui_related_list action="INSERT_OR_UPDATE"><calculated_name>Port Connection - NSPro</calculated_name><filter/><name>x_g_sonc_ns_pro_port_connection</name><order_by/><position/><related_list/><sys_class_name>sys_ui_related_list</sys_class_name><sys_created_by>wbbusby</sys_created_by><sys_created_on>2023-12-08 13:19:19</sys_created_on><sys_domain>global</sys_domain><sys_domain_path>/</sys_domain_path><sys_id>a35d2ae41b07b150824752c1604bcbdf</sys_id><sys_mod_count>0</sys_mod_count><sys_name>Port Connection - NSPro</sys_name><sys_package display_value="NS Pro" source="x_g_sonc_ns_pro">b5683ae81b157110824752c1604bcbc0</sys_package><sys_policy/><sys_scope display_value="NS Pro">b5683ae81b157110824752c1604bcbc0</sys_scope><sys_update_name>sys_ui_related_x_g_sonc_ns_pro_port_connection_nspro</sys_update_name><sys_updated_by>wbbusby</sys_updated_by><sys_updated_on>2023-12-08 13:19:19</sys_updated_on><sys_user/><view display_value="NSPro" name="nspro">7d269f741be1fd10824752c1604bcb31</view><view_name/></sys_ui_related_list></sys_ui_related></record_update>]]></payload>
        <payload_hash>-359679006</payload_hash>
        <record_name>Port Connection</record_name>
        <reverted_from/>
        <source>ef793e2c1b157110824752c1604bcbc8</source>
        <source_table>sys_update_set</source_table>
        <state>current</state>
        <sys_created_by>wbbusby</sys_created_by>
        <sys_created_on>2023-12-08 13:19:19</sys_created_on>
        <sys_id>635daae41b07b150824752c1604bcb0d</sys_id>
        <sys_mod_count>0</sys_mod_count>
        <sys_recorded_at>18c499520f20000001</sys_recorded_at>
        <sys_updated_by>wbbusby</sys_updated_by>
        <sys_updated_on>2023-12-08 13:19:19</sys_updated_on>
        <type>Related Lists</type>
        <update_guid>675daae48307b150d6d1d2ff2bffaf0c</update_guid>
        <update_guid_history>675daae48307b150d6d1d2ff2bffaf0c:-359679006</update_guid_history>
    </sys_update_version>
    <sys_metadata_delete action="INSERT_OR_UPDATE">
        <sys_audit_delete/>
        <sys_class_name>sys_metadata_delete</sys_class_name>
        <sys_created_by>wbbusby</sys_created_by>
        <sys_created_on>2024-02-15 17:50:31</sys_created_on>
        <sys_db_object display_value="" name="sys_ui_related_list">sys_ui_related_list</sys_db_object>
        <sys_id>50f667665018452c9008b7bec600d104</sys_id>
        <sys_metadata>a35d2ae41b07b150824752c1604bcbdf</sys_metadata>
        <sys_mod_count>0</sys_mod_count>
        <sys_name>Port Connection - NSPro</sys_name>
        <sys_package display_value="NS Pro" source="x_g_sonc_ns_pro">b5683ae81b157110824752c1604bcbc0</sys_package>
        <sys_parent display_value="Port Connection">c94101a91b613550824752c1604bcb99</sys_parent>
        <sys_policy/>
        <sys_scope display_value="NS Pro">b5683ae81b157110824752c1604bcbc0</sys_scope>
        <sys_scope_delete display_value="">bd97b329774640a2bbe5a7af5f2552c9</sys_scope_delete>
        <sys_update_name>sys_ui_related_x_g_sonc_ns_pro_port_connection_nspro</sys_update_name>
        <sys_update_version display_value="sys_ui_related_x_g_sonc_ns_pro_port_connection_nspro">635daae41b07b150824752c1604bcb0d</sys_update_version>
        <sys_updated_by>wbbusby</sys_updated_by>
        <sys_updated_on>2024-02-15 17:50:31</sys_updated_on>
    </sys_metadata_delete>
</record_update>
