<?xml version="1.0" encoding="UTF-8"?><record_update sys_domain="global" table="sys_ux_page_property">
    <sys_ux_page_property action="DELETE">
        <choices/>
        <description/>
        <name>actionConfigId</name>
        <page display_value="">4e1bd8ba70a2799015ce089c7de4424d</page>
        <required_translations>[]</required_translations>
        <route/>
        <suffix/>
        <sys_class_name>sys_ux_page_property</sys_class_name>
        <sys_created_by>wbbusby</sys_created_by>
        <sys_created_on>2023-11-20 05:55:11</sys_created_on>
        <sys_domain>global</sys_domain>
        <sys_domain_path>global</sys_domain_path>
        <sys_id>0e1bd8ba0da27990586e8539b18e503a</sys_id>
        <sys_mod_count>0</sys_mod_count>
        <sys_name>actionConfigId</sys_name>
        <sys_package display_value="NS Pro" source="x_g_sonc_ns_pro">b5683ae81b157110824752c1604bcbc0</sys_package>
        <sys_policy/>
        <sys_scope display_value="NS Pro">b5683ae81b157110824752c1604bcbc0</sys_scope>
        <sys_update_name>sys_ux_page_property_0e1bd8ba0da27990586e8539b18e503a</sys_update_name>
        <sys_updated_by>wbbusby</sys_updated_by>
        <sys_updated_on>2023-11-20 05:55:11</sys_updated_on>
        <type>string</type>
        <unique_name>x_g_sonc_ns_pro.4e1bd8ba70a2799015ce089c7de4424d.root.actionConfigId</unique_name>
        <value>df28e3db0f1210107d20409dc4767ee0</value>
    </sys_ux_page_property>
    <sys_update_version action="INSERT_OR_UPDATE">
        <action>DELETE</action>
        <application display_value="NS Pro">b5683ae81b157110824752c1604bcbc0</application>
        <file_path/>
        <instance_id>efe2cdc7db351c10bc8b7f693296192d</instance_id>
        <instance_name>ncgovappdev</instance_name>
        <name>sys_ux_page_property_0e1bd8ba0da27990586e8539b18e503a</name>
        <payload><![CDATA[<?xml version="1.0" encoding="UTF-8"?><record_update sys_domain="global" table="sys_ux_page_property"><sys_ux_page_property action="INSERT_OR_UPDATE"><choices/><description/><name>actionConfigId</name><page display_value="">4e1bd8ba70a2799015ce089c7de4424d</page><required_translations>[]</required_translations><route/><suffix/><sys_class_name>sys_ux_page_property</sys_class_name><sys_created_by>wbbusby</sys_created_by><sys_created_on>2023-11-20 05:55:11</sys_created_on><sys_domain>global</sys_domain><sys_domain_path>global</sys_domain_path><sys_id>0e1bd8ba0da27990586e8539b18e503a</sys_id><sys_mod_count>0</sys_mod_count><sys_name>actionConfigId</sys_name><sys_package display_value="NS Pro" source="x_g_sonc_ns_pro">b5683ae81b157110824752c1604bcbc0</sys_package><sys_policy/><sys_scope display_value="NS Pro">b5683ae81b157110824752c1604bcbc0</sys_scope><sys_update_name>sys_ux_page_property_0e1bd8ba0da27990586e8539b18e503a</sys_update_name><sys_updated_by>wbbusby</sys_updated_by><sys_updated_on>2023-11-20 05:55:11</sys_updated_on><type>string</type><unique_name>x_g_sonc_ns_pro.4e1bd8ba70a2799015ce089c7de4424d.root.actionConfigId</unique_name><value>df28e3db0f1210107d20409dc4767ee0</value></sys_ux_page_property></record_update>]]></payload>
        <payload_hash>1820801624</payload_hash>
        <record_name>actionConfigId</record_name>
        <reverted_from/>
        <source>1d082b221b323110824752c1604bcb50</source>
        <source_table>sys_upgrade_history</source_table>
        <state>previous</state>
        <sys_created_by/>
        <sys_created_on>2023-12-02 12:27:43</sys_created_on>
        <sys_id>7b5481c547937950f4af2ad2e16d43c4</sys_id>
        <sys_mod_count/>
        <sys_recorded_at>18c2a7fba180000000</sys_recorded_at>
        <sys_updated_by/>
        <sys_updated_on/>
        <type>UX Page Property</type>
        <update_guid>3b5481c549937950cc2ea1b9ecaf91c4</update_guid>
        <update_guid_history>3b5481c549937950cc2ea1b9ecaf91c4:1820801624</update_guid_history>
    </sys_update_version>
    <sys_metadata_delete action="INSERT_OR_UPDATE">
        <sys_audit_delete/>
        <sys_class_name>sys_metadata_delete</sys_class_name>
        <sys_created_by>wbbusby</sys_created_by>
        <sys_created_on>2023-12-22 05:13:15</sys_created_on>
        <sys_db_object display_value="" name="sys_ux_page_property">sys_ux_page_property</sys_db_object>
        <sys_id>1b3c1839ecfb4a7e9214b608f184fbd9</sys_id>
        <sys_metadata>0e1bd8ba0da27990586e8539b18e503a</sys_metadata>
        <sys_mod_count>0</sys_mod_count>
        <sys_name>actionConfigId</sys_name>
        <sys_package display_value="NS Pro" source="x_g_sonc_ns_pro">b5683ae81b157110824752c1604bcbc0</sys_package>
        <sys_parent/>
        <sys_policy/>
        <sys_scope display_value="NS Pro">b5683ae81b157110824752c1604bcbc0</sys_scope>
        <sys_scope_delete display_value="">bd97b329774640a2bbe5a7af5f2552c9</sys_scope_delete>
        <sys_update_name>sys_ux_page_property_0e1bd8ba0da27990586e8539b18e503a</sys_update_name>
        <sys_update_version display_value="sys_ux_page_property_0e1bd8ba0da27990586e8539b18e503a">7b5481c547937950f4af2ad2e16d43c4</sys_update_version>
        <sys_updated_by>wbbusby</sys_updated_by>
        <sys_updated_on>2023-12-22 05:13:15</sys_updated_on>
    </sys_metadata_delete>
</record_update>
